{"name":"Andrew Heisler Designs and Consultation","tagline":"A website by you, for you.","body":"### Welcome to my website.\r\nI am a web designer/SEO consultant/Social Media Consultant who has 2+ years employed in the field, and 4+ in personal and freelance designing.\r\n\r\nI employ modern web standards for the most pleasant viewing experience on all devices for a large majority of customers.\r\n\r\n```\r\nMy skills\r\n* HTML/CSS/JS\r\n* Python\r\n* PHP\r\n* Photoshop/Illustrator\r\n* .NET\r\n* Microsoft Office 2010,2013\r\n```\r\n\r\nPortfolio\r\n```\r\n\r\n```\r\n\r\n## Contact me\r\n* Email [acgheisler@gmail.com](mailto:acgheisler@gmail.com)\r\n* Github [acgh213](https://github.com/acgh213)","google":"UA-55346298-1","note":"Don't delete this file! It's used internally to help with page regeneration."}